{
   "weathers":[
      {
         "currentWeather":{
            "condition":"Patchy light snow",
            "humidity":93,
            "imgName":"20",
            "imgUrl":"",
            "pressure":1004,
            "temperature":27,
            "windDirection":"S",
            "windSpeed":7
         },
         "forecast":[
            {
               "condition":"Moderate snow",
               "day":"Tue",
               "highTemperature":35,
               "imgName":"19",
               "imgUrl":"",
               "lowTemperature":6
            },
            {
               "condition":"Partly Cloudy ",
               "day":"Wed",
               "highTemperature":17,
               "imgName":"03",
               "imgUrl":"",
               "lowTemperature":-7
            },
            {
               "condition":"Overcast ",
               "day":"Thu",
               "highTemperature":17,
               "imgName":"07",
               "imgUrl":"",
               "lowTemperature":3
            }
         ],
         "location":{
            "city":"Madison",
            "latitude":0,
            "locationCode":"",
            "longitude":0,
            "stateOrCountry":"Wisconsin"
         },
         "moreInformationLink":"http://www.worldweatheronline.com/weather.aspx?q=Madison%2C+Wisconsin%2C+United+States+of+America",
         "pressureUnit":"mb",
         "temperatureUnit":"F",
         "windUnit":"mi"
      }
   ],
   "errors":[

   ],
   "serviceName":"World Weather Online",
   "serviceUrl":"http://www.worldweatheronline.com/",
   "isGuest":false
}
